hardlink/__init__.py
hardlink/base.py
hardlink-0.2.dist-info/DESCRIPTION.rst
hardlink-0.2.dist-info/entry_points.txt
hardlink-0.2.dist-info/METADATA
hardlink-0.2.dist-info/metadata.json
hardlink-0.2.dist-info/RECORD
hardlink-0.2.dist-info/top_level.txt
hardlink-0.2.dist-info/WHEEL
