Metadata-Version: 2.0
Name: hardlink
Version: 0.2
Summary: Copy files and merge directories using hard links.
Home-page: https://github.com/mrmachine/hardlink
Author: Tai Lee
Author-email: real.human@mrmachine.net
License: MIT
Platform: UNKNOWN
